{
  "generatedAt": "2026-06-29T04:06:28Z",
  "stories": [
    {
      "title": "Sources: Suns land Bridges in deal with Hornets",
      "link": "https://www.espn.com/nba/story/_/id/49208142/sources-hornets-trade-veteran-miles-bridges-suns",
      "pubDate": "Sun, 28 Jun 2026 23:50:37 EST",
      "summary": "The Hornets are trading Miles Bridges, a 2029 first-round pick and a second-round pick to the Suns for Grayson Allen, Royce O'Neale and a 2033 first.",
      "source": "ESPN",
      "image": "https://a.espncdn.com/combiner/i?img=%2Fphoto%2F2025%2F1230%2Fr1594885_1296x729_16%2D9.jpg",
      "pubDateIso": "2026-06-28T23:50:37-05:00"
    },
    {
      "title": "Gray no-hitter ends in 8th, Red Sox sweep Yankees",
      "link": "https://www.espn.com/mlb/story/_/id/49212701/red-sox-rally-10th-complete-four-game-sweep-yankees",
      "pubDate": "Sun, 28 Jun 2026 23:50:37 EST",
      "summary": "Jarren Duran singled home the winning run to cap a three-run rally in the 10th inning after Boston blew a two-run lead in the ninth, and the Red Sox finished a four-game sweep of the rival New York Yankees with a 5-4 victory Sunday night at Fenway Park.",
      "source": "ESPN",
      "image": "https://a3.espncdn.com/combiner/i?img=%2Fphoto%2F2026%2F0629%2Fr1681361_1296x729_16%2D9.jpg",
      "pubDateIso": "2026-06-28T23:50:37-05:00"
    },
    {
      "title": "Scheffler, Hovland set for Mon. playoff at Travele...",
      "link": "https://www.espn.com/golf/story/_/id/49211696/scheffler-forces-monday-playoff-hovland-travelers",
      "pubDate": "Sun, 28 Jun 2026 23:50:37 EST",
      "summary": "Scottie Scheffler made an 8-foot par putt on the 18th hole Sunday, forcing a sudden-death playoff against Viktor Hovland on Monday at the rain-delayed Travelers.",
      "source": "ESPN",
      "image": "https://a1.espncdn.com/combiner/i?img=%2Fphoto%2F2026%2F0629%2Fr1681319_1296x729_16%2D9.jpg",
      "pubDateIso": "2026-06-28T23:50:37-05:00"
    },
    {
      "title": "Ancelotti refuses to engage in Japan 'mind games'",
      "link": "https://www.espn.com/soccer/story/_/id/49211268/brazil-manager-carlo-ancelotti-refuses-engage-japan-mind-games-ahead-round-32-clash-world-cup",
      "pubDate": "Sun, 28 Jun 2026 23:50:37 EST",
      "summary": "Brazil manager Carlo Ancelotti refused to engage in \"mind games\" ahead of the round-of-32 clash with Japan on Monday.",
      "source": "ESPN",
      "image": "https://a4.espncdn.com/combiner/i?img=%2Fphoto%2F2026%2F0629%2Fr1681308_1296x729_16%2D9.jpg",
      "pubDateIso": "2026-06-28T23:50:37-05:00"
    },
    {
      "title": "Source: Fire in final stage of deal for Lewandowsk...",
      "link": "https://www.espn.com/soccer/story/_/id/49211267/chicago-fire-signing-robert-lewandowski",
      "pubDate": "Sun, 28 Jun 2026 23:50:38 EST",
      "summary": "Chicago Fire FC and Robert Lewandowski are finalizing the details of a deal that would see the Poland striker move to MLS this summer, a source confirmed to ESPN.",
      "source": "ESPN",
      "image": "https://a3.espncdn.com/combiner/i?img=%2Fphoto%2F2026%2F0628%2Fr1681303_1296x729_16%2D9.jpg",
      "pubDateIso": "2026-06-28T23:50:38-05:00"
    }
  ]
}