{
  "generatedAt": "2026-05-27T20:55:05Z",
  "stories": [
    {
      "title": "Four trade candidates, 16 offers, just one deal: W...",
      "link": "https://www.espn.com/nfl/story/_/id/48816864/2026-nfl-offseason-trade-offers-best-deals-coleman-kmet-richardson-thibodeaux",
      "pubDate": "Wed, 27 May 2026 15:36:30 EST",
      "summary": "We proposed trade offers for Keon Coleman, Cole Kmet, Anthony Richardson Sr. and Kayvon Thibodeaux. Could any of them be on the move?",
      "source": "ESPN",
      "image": "https://a3.espncdn.com/combiner/i?img=%2Fphoto%2F2026%2F0509%2Fr1655809_1296x729_16%2D9.jpg",
      "pubDateIso": "2026-05-27T15:36:30-05:00"
    },
    {
      "title": "Who are the top quarterbacks in next year's NFL dr...",
      "link": "https://www.espn.com/nfl/draft2027/story/_/id/48828988/2027-nfl-draft-quarterback-class-top-prospects-manning-moore-carr",
      "pubDate": "Wed, 27 May 2026 15:36:30 EST",
      "summary": "The 2027 QB draft class should be loaded. Arch Manning, Dante Moore, CJ Carr and Trinidad Chambliss top the list.",
      "source": "ESPN",
      "image": "https://a1.espncdn.com/combiner/i?img=%2Fphoto%2F2026%2F0522%2Fr1662057_1296x729_16%2D9.jpg",
      "pubDateIso": "2026-05-27T15:36:30-05:00"
    },
    {
      "title": "Packers' Jacobs out of jail; investigation ongoing...",
      "link": "https://www.espn.com/nfl/story/_/id/48892463/packers-josh-jacobs-released-jail-investigation-ongoing",
      "pubDate": "Wed, 27 May 2026 16:40:22 EST",
      "summary": "Packers running back Josh Jacobs has been released from jail Wednesday amid an ongoing investigation following his arrest on several domestic violence charges.",
      "source": "ESPN",
      "image": "https://a3.espncdn.com/combiner/i?img=%2Fphoto%2F2025%2F1123%2Fr1579541_1296x729_16%2D9.jpg",
      "pubDateIso": "2026-05-27T16:40:22-05:00"
    },
    {
      "title": "Bipartisan college sports bill proposes salary cap...",
      "link": "https://www.espn.com/espn/story/_/id/48891780/bipartisan-college-sports-bill-proposes-salary-cap-transfer-limit",
      "pubDate": "Wed, 27 May 2026 16:40:22 EST",
      "summary": "A group of U.S. senators introduced a bipartisan college sports bill that aims to regulate payments to players, limit transfers and restrict coach movement during the season.",
      "source": "ESPN",
      "image": "https://a.espncdn.com/combiner/i?img=%2Fphoto%2F2024%2F1008%2Fr1398075_1296x729_16%2D9.jpg",
      "pubDateIso": "2026-05-27T16:40:22-05:00"
    },
    {
      "title": "Vrabel says family-football balance 'really good'",
      "link": "https://www.espn.com/nfl/story/_/id/48892784/patriots-mike-vrabel-no-regrets-stepping-away-draft",
      "pubDate": "Wed, 27 May 2026 16:40:23 EST",
      "summary": "Coach Mike Vrabel said Wednesday during the Patriots' second OTA that the process of balancing family and football is going \"really good\"",
      "source": "ESPN",
      "image": "https://a1.espncdn.com/combiner/i?img=%2Fphoto%2F2026%2F0527%2Fr1664492_1296x729_16%2D9.jpg",
      "pubDateIso": "2026-05-27T16:40:23-05:00"
    }
  ]
}