{
  "generatedAt": "2026-06-08T21:28:03Z",
  "stories": [
    {
      "title": "'He's us -- except he's very good at basketball': ...",
      "link": "https://www.espn.com/nba/story/_/id/48995150/how-jalen-brunson-became-king-new-york-knicks-nba-finals",
      "pubDate": "Mon, 8 Jun 2026 17:10:54 EST",
      "summary": "Brunson's appeal in New York centers around one idea: People might appreciate glitz and glamour -- but they respect guts and guile even more.",
      "source": "ESPN",
      "image": "https://a2.espncdn.com/combiner/i?img=%2Fphoto%2F2026%2F0608%2Fr1669592_1296x729_16%2D9.jpg",
      "pubDateIso": "2026-06-08T17:10:54-05:00"
    },
    {
      "title": "The Knicks solved their minutes puzzle just in tim...",
      "link": "https://www.espn.com/nba/story/_/id/48987208/nba-finals-2026-knicks-spurs-game-3-madison-square-garden-robinson-shamet-bench",
      "pubDate": "Mon, 8 Jun 2026 17:10:54 EST",
      "summary": "Here's how New York embraced its bench and overcame one of its biggest obstacles to a title.",
      "source": "ESPN",
      "image": "https://a4.espncdn.com/combiner/i?img=%2Fphoto%2F2026%2F0607%2Fr1669310_1296x729_16%2D9.jpg",
      "pubDateIso": "2026-06-08T17:10:54-05:00"
    },
    {
      "title": "Sorsby granted injunction, eligible to play in '26...",
      "link": "https://www.espn.com/college-football/story/_/id/49000177/brendan-sorsby-granted-injunction-vs-ncaa-eligible-play-2026",
      "pubDate": "Mon, 8 Jun 2026 17:08:33 EST",
      "summary": "Texas Tech star quarterback Brendan Sorsby has been granted a temporary injunction against the NCAA and will be eligible to play for the Red Raiders in 2026.",
      "source": "ESPN",
      "image": "https://a.espncdn.com/combiner/i?img=%2Fphoto%2F2026%2F0427%2Fr1650028_1296x729_16%2D9.jpg",
      "pubDateIso": "2026-06-08T17:08:33-05:00"
    },
    {
      "title": "Aiyuk appears to imply 49ers 'scared' to cut him",
      "link": "https://www.espn.com/nfl/story/_/id/49002414/brandon-aiyuk-appears-imply-49ers-scared-release-him",
      "pubDate": "Mon, 8 Jun 2026 17:08:33 EST",
      "summary": "Brandon Aiyuk posted a video to Instagram on Sunday, appearing to imply that the 49ers are afraid to release him because he could land elsewhere and eventually make them regret letting him go.",
      "source": "ESPN",
      "image": "https://a1.espncdn.com/combiner/i?img=%2Fphoto%2F2026%2F0608%2Fr1669910_1296x729_16%2D9.jpg",
      "pubDateIso": "2026-06-08T17:08:33-05:00"
    },
    {
      "title": "Chiefs reunite with CB Sneed 2 years after trade",
      "link": "https://www.espn.com/nfl/story/_/id/49002989/chiefs-signing-veteran-cb-ljarius-sneed-agents-say",
      "pubDate": "Mon, 8 Jun 2026 17:08:33 EST",
      "summary": "The Chiefs are signing cornerback L'Jarius Sneed, his agents, the Katz Brothers, told ESPN's Adam Schefter.",
      "source": "ESPN",
      "image": "https://a.espncdn.com/combiner/i?img=%2Fphoto%2F2024%2F0305%2Fr1300492_1296x729_16%2D9.jpg",
      "pubDateIso": "2026-06-08T17:08:33-05:00"
    }
  ]
}