{
  "generatedAt": "2026-04-21T16:17:44Z",
  "stories": [
    {
      "title": "NFL draft rankings: Kiper finalizes his Big Board with the top 150 prospects, best at every position",
      "link": "https://www.espn.com/nfl/draft2026/story/_/id/46573669/2026-nfl-draft-rankings-mel-kiper-big-board-top-prospects-players-positions",
      "pubDate": "Tue, 21 Apr 2026 11:03:57 EST",
      "summary": "Mel Kiper Jr. updated his NFL draft rankings one last time. His Big Board stacks 150 prospects -- starting with Fernando Mendoza -- and goes deep at every position.",
      "image": "https://a3.espncdn.com/combiner/i?img=%2Fphoto%2F2026%2F0114%2Fr1600631_1296x729_16%2D9.jpg",
      "source": "ESPN",
      "pubDateIso": "2026-04-21T11:03:57-05:00"
    },
    {
      "title": "Reid's final NFL mock draft: We projected fits for all 32 teams across seven rounds",
      "link": "https://www.espn.com/nfl/draft2026/story/_/id/48480079/2026-nfl-mock-draft-seven-rounds-257-picks-predictions-jordan-reid-fits",
      "pubDate": "Tue, 21 Apr 2026 11:03:57 EST",
      "summary": "Jordan Reid projected every single pick for this week's NFL draft, from the Raiders' selection at No. 1 to Mr. Irrelevant.",
      "image": "https://a4.espncdn.com/combiner/i?img=%2Fphoto%2F2026%2F0415%2F260420_nfl_jordan%2Dreid%2D7th%2Dmock_16x9.jpg",
      "source": "ESPN",
      "pubDateIso": "2026-04-21T11:03:57-05:00"
    },
    {
      "title": "Donovan leaves Bulls amid sweeping changes",
      "link": "https://www.espn.com/nba/story/_/id/48550436/sources-billy-donovan-decides-step-bulls-coach",
      "pubDate": "Tue, 21 Apr 2026 12:06:21 EST",
      "summary": "Billy Donovan has decided to step down as head coach of the Bulls after six seasons.",
      "image": "https://a4.espncdn.com/combiner/i?img=%2Fphoto%2F2025%2F0727%2Fr1524287_1296x729_16%2D9.jpg",
      "source": "ESPN",
      "pubDateIso": "2026-04-21T12:06:21-05:00"
    },
    {
      "title": "Sources: Tomlin joining NBC as studio analyst",
      "link": "https://www.espn.com/nfl/story/_/id/48551327/mike-tomlin-joins-nbc-nfl-studio-analyst-sources-confirm",
      "pubDate": "Tue, 21 Apr 2026 12:06:21 EST",
      "summary": "Former Steelers coach Mike Tomlin is joining NBC's Sunday night pregame show, \"Football Night in America,\" as a studio analyst, sources confirmed to ESPN.",
      "image": "https://a.espncdn.com/combiner/i?img=%2Fphoto%2F2026%2F0113%2Fr1599934_1296x729_16%2D9.jpg",
      "source": "ESPN",
      "pubDateIso": "2026-04-21T12:06:21-05:00"
    },
    {
      "title": "Jets GM: Don't misread nixed visit with DE Bailey",
      "link": "https://www.espn.com/nfl/story/_/id/48551302/jets-gm-read-cancelled-visit-de-prospect-bailey",
      "pubDate": "Tue, 21 Apr 2026 12:06:21 EST",
      "summary": "Jets GM Darren Mougey said Tuesday that fans should not \"look too much\" into the cancellation of last week's predraft visit with DE prospect David Bailey, who could be their selection with the No. 2 pick.",
      "image": "https://a3.espncdn.com/combiner/i?img=%2Fphoto%2F2026%2F0421%2Fr1646969_1296x729_16%2D9.jpg",
      "source": "ESPN",
      "pubDateIso": "2026-04-21T12:06:21-05:00"
    }
  ]
}