{
  "generatedAt": "2026-07-09T18:17:15Z",
  "stories": [
    {
      "title": "How are Super Bowl rosters built? Barnwell went po...",
      "link": "https://www.espn.com/nfl/story/_/id/49309306/2026-nfl-season-super-bowl-roster-building-positions-draft-signings-trades",
      "pubDate": "Thu, 9 Jul 2026 13:50:09 EST",
      "summary": "Do teams need first-round QBs to reach the Super Bowl? Is it crucial to spend big on No. 1 receivers and top-tier edge rushers? Let's sort through rosters from the past 15 Super Bowls.",
      "source": "ESPN",
      "image": "https://a4.espncdn.com/combiner/i?img=%2Fphoto%2F2026%2F0708%2Fr1686643_1296x729_16%2D9.jpg",
      "pubDateIso": "2026-07-09T13:50:09-05:00"
    },
    {
      "title": "Why Year 2 of Ben Johnson has a different vibe wit...",
      "link": "https://www.espn.com/nfl/story/_/id/49306666/why-year-2-ben-johnson-different-vibe-bears",
      "pubDate": "Thu, 9 Jul 2026 13:50:09 EST",
      "summary": "Johnson established himself in Year 1, but success established expectations.",
      "source": "ESPN",
      "image": "https://a3.espncdn.com/combiner/i?img=%2Fphoto%2F2026%2F0708%2Fr1686435_1296x729_16%2D9.jpg",
      "pubDateIso": "2026-07-09T13:50:09-05:00"
    },
    {
      "title": "Sources: UCLA lands possible top NBA draft pick",
      "link": "https://www.espn.com/mens-college-basketball/story/_/id/49315186/sources-nikola-kusturica-possible-no-1-nba-draft-pick-chooses-ucla",
      "pubDate": "Thu, 9 Jul 2026 13:58:15 EST",
      "summary": "Nikola Kusturica has reached a multiyear agreement to play for UCLA, giving the Bruins an early contender for the No. 1 pick in the 2028 NBA draft.",
      "source": "ESPN",
      "image": "https://a2.espncdn.com/combiner/i?img=%2Fphoto%2F2026%2F0709%2Fr1686857_1296x729_16%2D9.jpg",
      "pubDateIso": "2026-07-09T13:58:15-05:00"
    },
    {
      "title": "Ducks match Flyers' $90M offer to Carlsson",
      "link": "https://www.espn.com/nhl/story/_/id/49316039/ducks-match-flyers-five-year-90m-offer-leo-carlsson",
      "pubDate": "Thu, 9 Jul 2026 13:58:15 EST",
      "summary": "The Ducks have matched the Flyers' five-year offer sheet for star 21-year-old center Leo Carlsson that is worth an NHL-high $18 million per season.",
      "source": "ESPN",
      "image": "https://a1.espncdn.com/combiner/i?img=%2Fphoto%2F2026%2F0706%2Fr1685337_1296x729_16%2D9.jpg",
      "pubDateIso": "2026-07-09T13:58:15-05:00"
    },
    {
      "title": "Sources: Pulisic has microfracture, bone bruise",
      "link": "https://www.espn.com/soccer/story/_/id/49315041/usa-christian-pulisic-suffered-microfracture-belgium-sources",
      "pubDate": "Thu, 9 Jul 2026 13:58:15 EST",
      "summary": "USMNT and AC Milan attacker Christian Pulisic sustained a bone bruise and microfracture in his lower leg and will be sidelined for several weeks, U.S. Soccer confirmed on Thursday.",
      "source": "ESPN",
      "image": "https://a4.espncdn.com/combiner/i?img=%2Fphoto%2F2026%2F0707%2Fr1685654_1296x729_16%2D9.jpg",
      "pubDateIso": "2026-07-09T13:58:15-05:00"
    }
  ]
}